{"name":"gimp","description":"GNU Image Manipulation Program\n GIMP is an advanced picture editor. You can use it to edit, enhance, and\n retouch photos and scans, create drawings, and make your own images.\n It has a large collection of professional-level editing tools and\n filters, similar to the ones you might find in Photoshop. Numerous\n fine-control settings and features like layers, paths, masks, and\n scripting give you total control over your images.\n .\n Many image file formats are supported, including JPEG, Photoshop (.psd),\n and Paint Shop Pro (.psp) files. It can also be used to scan and print\n photos.\n .\n To open files remotely (like over HTTP), install the gvfs-backends\n package.\n .\n To use a MIDI device (like a musical keyboard) as an input controller in GIMP,\n install libasound2 and read the how-to at /usr/share/doc/gimp/README.MIDI","dependencies":[{"name":"libgimp2.0","alternates":[]},{"name":"libgimp2.0","alternates":[]},{"name":"gimp-data","alternates":[]},{"name":"gimp-data","alternates":[]},{"name":"python-gtk2","alternates":[]},{"name":"libgdk-pixbuf2.0-0","alternates":[]},{"name":"libaa1","alternates":[]},{"name":"libbabl-0.1-0","alternates":[]},{"name":"libbz2-1.0","alternates":[]},{"name":"libc6","alternates":[]},{"name":"libcairo2","alternates":[]},{"name":"libdbus-1-3","alternates":[]},{"name":"libdbus-glib-1-2","alternates":[]},{"name":"libexif12","alternates":[]},{"name":"libfontconfig1","alternates":[]},{"name":"libfreetype6","alternates":[]},{"name":"libgegl-0.3-0","alternates":[]},{"name":"libglib2.0-0","alternates":[]},{"name":"libgs9","alternates":[]},{"name":"libgtk2.0-0","alternates":[]},{"name":"libgudev-1.0-0","alternates":[]},{"name":"libjpeg8","alternates":[]},{"name":"liblcms2-2","alternates":[]},{"name":"libmng2","alternates":[]},{"name":"libpango-1.0-0","alternates":[]},{"name":"libpangocairo-1.0-0","alternates":[]},{"name":"libpangoft2-1.0-0","alternates":[]},{"name":"libpng16-16","alternates":[]},{"name":"libpoppler-glib8","alternates":[]},{"name":"librsvg2-2","alternates":[]},{"name":"libtiff5","alternates":[]},{"name":"libwmf0.2-7","alternates":[]},{"name":"libx11-6","alternates":[]},{"name":"libxcursor1","alternates":[]},{"name":"libxext6","alternates":[]},{"name":"libxfixes3","alternates":[]},{"name":"libxmu6","alternates":[]},{"name":"libxpm4","alternates":[]},{"name":"zlib1g","alternates":[]},{"name":"python2.7","alternates":[]},{"name":"python:any","alternates":[]}],"reverseDependencies":[]}