{"name":"libhtml-format-perl","description":"module for transforming HTML into various formats\n HTML::Formatter is a base class for various formatters, which are modules\n that traverse an HTML syntax tree and produce various output file formats.\n There are currently three formatter classes included:\n .\n  * HTML::FormatText for converting to plain human-readable text\n  * HTML::FormatPS for converting to PostScript\n  * HTML::FormatRTF for converting to Microsoft's Rich Text Format (RTF)","dependencies":[{"name":"perl","alternates":[]},{"name":"libfont-afm-perl","alternates":[]},{"name":"libhtml-tree-perl","alternates":[]}],"reverseDependencies":[]}