{"name":"librsvg2-2","description":"SAX-based renderer library for SVG files (runtime)\n The rsvg library is an efficient renderer for Scalable Vector Graphics\n (SVG) pictures.\n .\n This package contains the runtime library, necessary to run\n applications using librsvg.","dependencies":[{"name":"libc6","alternates":[]},{"name":"libcairo2","alternates":[]},{"name":"libcroco3","alternates":[]},{"name":"libfontconfig1","alternates":[]},{"name":"libgdk-pixbuf2.0-0","alternates":[]},{"name":"libglib2.0-0","alternates":[]},{"name":"libpango-1.0-0","alternates":[]},{"name":"libpangocairo-1.0-0","alternates":[]},{"name":"libpangoft2-1.0-0","alternates":[]},{"name":"libxml2","alternates":[]}],"reverseDependencies":[]}