{"name":"libwoff1","description":"library for converting fonts to WOFF 2.0\n woff2 is a library for converting fonts from the TTF format to the WOFF 2.0\n format. The library also allows decompression from WOFF 2.0 to TTF.\n .\n The WOFF 2.0 format uses the Brotli compression algorithm to compress fonts\n suitable for use in CSS @font-face rules. WOFF 2.0 is a W3C Candidate\n Recommendation.","dependencies":[{"name":"libbrotli1","alternates":[]},{"name":"libc6","alternates":[]},{"name":"libgcc1","alternates":[]},{"name":"libstdc++6","alternates":[]}],"reverseDependencies":[]}