{"name":"mutter","description":"lightweight GTK+ window manager\n Mutter is a small window manager, using GTK+ and Clutter to do\n everything.\n .\n Mutter is the clutter-based evolution of Metacity, which, as the\n author says, is a \"Boring window manager for the adult in you. Many\n window managers are like Marshmallow Froot Loops; Metacity is like\n Cheerios.\"\n .\n This package contains the core binaries.","dependencies":[{"name":"libc6","alternates":[]},{"name":"libglib2.0-0","alternates":[]},{"name":"libmutter-2-0","alternates":[]},{"name":"libx11-6","alternates":[]},{"name":"libxcomposite1","alternates":[]},{"name":"mutter-common","alternates":[]},{"name":"gnome-settings-daemon","alternates":[]},{"name":"gsettings-desktop-schemas","alternates":[]},{"name":"zenity","alternates":[]}],"reverseDependencies":[]}