{"name":"printer-driver-foo2zjs-common","description":"printer driver for ZjStream-based printers - common files\n foo2zjs is an open source printer driver for printers that use the\n Zenographics ZjStream wire protocol for their print data, such as the\n Minolta magicolor 2200/2300/2430 DL, Minolta Color PageWorks/Pro L and\n HP LaserJet 1000/1005/1018/1020/1022. These printers are often\n erroneously referred to as \"winprinters\" or \"GDI printers\".\n .\n This package contains the architecture-independent files for\n printer-driver-foo2zjs.","dependencies":[{"name":"python3","alternates":[]},{"name":"xz-utils","alternates":[]}],"reverseDependencies":["cups","foo2zjs","printer-driver-foo2zjs","udev"]}