{"name":"python3-systemd","description":"Python 3 bindings for systemd\n This package contains Python 3 bindings for native access to the\n systemd facilities.\n .\n Functionality is separated into a number of modules:\n  * systemd.journal supports sending of structured messages to the\n    journal and reading journal files\n  * systemd.daemon wraps parts of libsystemd useful for writing daemons\n    and socket activation\n  * systemd.id128 provides functions for querying machine and boot\n    identifiers and a list of message identifiers provided by systemd\n  * systemd.login wraps parts of libsystemd used to query logged in\n    users and available seats and machines","dependencies":[{"name":"python3","alternates":[]},{"name":"python3","alternates":[]},{"name":"python3:any","alternates":[]},{"name":"libc6","alternates":[]},{"name":"libsystemd0","alternates":[]}],"reverseDependencies":[]}